decorator_plus/__init__.py
decorator_plus/version.py
django_decorator_plus-0.0.1.dev20150902190642.dist-info/DESCRIPTION.rst
django_decorator_plus-0.0.1.dev20150902190642.dist-info/METADATA
django_decorator_plus-0.0.1.dev20150902190642.dist-info/metadata.json
django_decorator_plus-0.0.1.dev20150902190642.dist-info/RECORD
django_decorator_plus-0.0.1.dev20150902190642.dist-info/top_level.txt
django_decorator_plus-0.0.1.dev20150902190642.dist-info/WHEEL
